{"path": "speaker/Rev._Spencer_Aalsburg", "name": "Aalsburg, Spencer", "letter": "A"}
{"path": "speaker/Brother_Aaron", "name": "Aaron", "letter": "A"}
{"path": "speaker/Larry_Aaron", "name": "Aaron, Larry", "letter": "A"}
{"path": "speaker/Lewis,_Aaron", "name": "Aaron, Lewis,", "letter": "A"}
{"path": "speaker/Lyjah_Aaron", "name": "Aaron, Lyjah", "letter": "A"}
{"path": "speaker/James_Aasgaard", "name": "Aasgaard, James", "letter": "A"}
{"path": "speaker/Paul_Aasman", "name": "Aasman, Paul", "letter": "A"}
{"path": "speaker/Richard_Aasman", "name": "Aasman, Richard", "letter": "A"}
{"path": "speaker/Dr._Berty_Ab", "name": "Ab, Berty", "letter": "A"}
{"path": "speaker/Emmanuel_Abadilla", "name": "Abadilla, Emmanuel", "letter": "A"}
{"path": "speaker/Pastor_Todd_L._Abbey", "name": "Abbey, Todd", "letter": "A"}
{"path": "speaker/Michael_Abbott_(UK)", "name": "Abbott (UK), Michael", "letter": "A"}
{"path": "speaker/Art_Abbott", "name": "Abbott, Art", "letter": "A"}
{"path": "speaker/Bill_Abbott", "name": "Abbott, Bill", "letter": "A"}
{"path": "speaker/John_Abbott", "name": "Abbott, John", "letter": "A"}
{"path": "speaker/Paul_Abbott", "name": "Abbott, Paul", "letter": "A"}
{"path": "speaker/Shawn_Abbott", "name": "Abbott, Shawn", "letter": "A"}
{"path": "speaker/Timo_Abbott", "name": "Abbott, Timo", "letter": "A"}
{"path": "speaker/Irfan_Abdullatif", "name": "Abdullatif, Irfan", "letter": "A"}
{"path": "speaker/Lester_Abella", "name": "Abella, Lester", "letter": "A"}
{"path": "speaker/Doug_Abels", "name": "Abels, Doug", "letter": "A"}
{"path": "speaker/Michael_Abels", "name": "Abels, Michael", "letter": "A"}
{"path": "speaker/Doug_Abendroth", "name": "Abendroth, Doug", "letter": "A"}
{"path": "speaker/Mike_Abendroth", "name": "Abendroth, Mike", "letter": "A"}
{"path": "speaker/Pat_Abendroth", "name": "Abendroth, Pat", "letter": "A"}
{"path": "speaker/Dr._Ab_Abercrombie", "name": "Abercrombie, Ab", "letter": "A"}
{"path": "speaker/Christian_Abernatha", "name": "Abernatha, Christian", "letter": "A"}
{"path": "speaker/Elder_Buddy_Abernathy", "name": "Abernathy, Buddy", "letter": "A"}
{"path": "speaker/Jeff_Abernathy", "name": "Abernathy, Jeff", "letter": "A"}
{"path": "speaker/Tim_Abernathy", "name": "Abernathy, Tim", "letter": "A"}
{"path": "speaker/Carole_Abernethy", "name": "Abernethy, Carole", "letter": "A"}
{"path": "speaker/Rev._Darryl_Abernethy", "name": "Abernethy, Darryl", "letter": "A"}
{"path": "speaker/Jay_Abisch", "name": "Abisch, Jay", "letter": "A"}
{"path": "speaker/Cunard_Llyod_Abiva", "name": "Abiva, Cunard Llyod", "letter": "A"}
{"path": "speaker/Craig_Abla", "name": "Abla, Craig", "letter": "A"}
{"path": "speaker/Jeffrey_Ables", "name": "Ables, Jeffrey", "letter": "A"}
{"path": "speaker/Robert_Aboagye", "name": "Aboagye, Robert", "letter": "A"}
{"path": "speaker/Philip_Abode", "name": "Abode, Philip", "letter": "A"}
{"path": "speaker/Rev._Geoffrey_Abraham", "name": "Abraham, Geoffrey", "letter": "A"}
{"path": "speaker/Matthew_Abraham", "name": "Abraham, Matthew", "letter": "A"}
{"path": "speaker/Samuel_Abraham", "name": "Abraham, Samuel", "letter": "A"}
{"path": "speaker/Zecharias_Abraham", "name": "Abraham, Zecharias", "letter": "A"}
{"path": "speaker/Gregg_Abrahamsen", "name": "Abrahamsen, Gregg", "letter": "A"}
{"path": "speaker/Ron_Abrahamsen", "name": "Abrahamsen, Ron", "letter": "A"}
{"path": "speaker/Tracy_Abrahamsen", "name": "Abrahamsen, Tracy", "letter": "A"}
{"path": "speaker/Dr._Carl_Abrams", "name": "Abrams, Carl", "letter": "A"}
{"path": "speaker/Cooper_Abrams", "name": "Abrams, Cooper", "letter": "A"}
{"path": "speaker/Grant_Abrams", "name": "Abrams, Grant", "letter": "A"}
{"path": "speaker/Aaron_Abramson", "name": "Abramson, Aaron", "letter": "A"}
{"path": "speaker/Fabi\u00e1n_Abreg\u00fa", "name": "Abreg\u00fa, Fabi\u00e1n", "letter": "A"}
{"path": "speaker/Carlos_Abreu", "name": "Abreu, Carlos", "letter": "A"}
{"path": "speaker/Joaqu\u00edn_Abreu", "name": "Abreu, Joaqu\u00edn", "letter": "A"}
{"path": "speaker/Tyler_Absher", "name": "Absher, Tyler", "letter": "A"}
{"path": "speaker/Brian_Abshire", "name": "Abshire, Brian", "letter": "A"}
{"path": "speaker/Hector_Acayturri", "name": "Acayturri, Hector", "letter": "A"}
{"path": "speaker/Manuel_Acedo", "name": "Acedo, Manuel", "letter": "A"}
{"path": "speaker/David_Acevedo", "name": "Acevedo, David", "letter": "A"}
{"path": "speaker/Frank_Acevedo", "name": "Acevedo, Frank", "letter": "A"}
{"path": "speaker/Rev_Paul_Acheson", "name": "Acheson, Paul", "letter": "A"}
{"path": "speaker/David_Achilles", "name": "Achilles, David", "letter": "A"}
{"path": "speaker/Aaron_Acker", "name": "Acker, Aaron", "letter": "A"}
{"path": "speaker/Bill_Acker", "name": "Acker, Bill", "letter": "A"}
{"path": "speaker/Dr_Roy_Ackerle", "name": "Ackerle, Roy", "letter": "A"}
{"path": "speaker/Paul_Ackerley", "name": "Ackerley, Paul", "letter": "A"}
{"path": "speaker/Ryan_Ackerman", "name": "Ackerman, Ryan", "letter": "A"}
{"path": "speaker/Ken_Ackers", "name": "Ackers, Ken", "letter": "A"}
{"path": "speaker/Christian_Acosta", "name": "Acosta, Christian", "letter": "A"}
{"path": "speaker/Chuy_Acosta", "name": "Acosta, Chuy", "letter": "A"}
{"path": "speaker/Luis_Acosta", "name": "Acosta, Luis", "letter": "A"}
{"path": "speaker/No\u00e9_Acosta", "name": "Acosta, No\u00e9", "letter": "A"}
{"path": "speaker/Nathan_Acre", "name": "Acre, Nathan", "letter": "A"}
{"path": "speaker/Seth_Acree", "name": "Acree, Seth", "letter": "A"}
{"path": "speaker/Mark_Acsay", "name": "Acsay, Mark", "letter": "A"}
{"path": "speaker/Julio_Acuna", "name": "Acuna, Julio", "letter": "A"}
{"path": "speaker/Ron_Adair", "name": "Adair, Ron", "letter": "A"}
{"path": "speaker/Tim_Adair", "name": "Adair, Tim", "letter": "A"}
{"path": "speaker/Peaslee,_Adam", "name": "Adam, Peaslee,", "letter": "A"}
{"path": "speaker/Elias_Adamo", "name": "Adamo, Elias", "letter": "A"}
{"path": "speaker/Nathan_Adamo", "name": "Adamo, Nathan", "letter": "A"}
{"path": "speaker/Bill_Adams_Jr.", "name": "Adams Jr, Bill", "letter": "A"}
{"path": "speaker/Dr._Robert_Adams,_Jr.", "name": "Adams Jr., Robert", "letter": "A"}
{"path": "speaker/Andy_Adams", "name": "Adams, Andy", "letter": "A"}
{"path": "speaker/Arthur_Adams", "name": "Adams, Arthur", "letter": "A"}
{"path": "speaker/Bill_Adams", "name": "Adams, Bill", "letter": "A"}
{"path": "speaker/Bob_Adams", "name": "Adams, Bob", "letter": "A"}
{"path": "speaker/Bobby_Adams", "name": "Adams, Bobby", "letter": "A"}
{"path": "speaker/Chris_Adams", "name": "Adams, Chris", "letter": "A"}
{"path": "speaker/Christopher_Adams", "name": "Adams, Christopher", "letter": "A"}
{"path": "speaker/Clint_Adams", "name": "Adams, Clint", "letter": "A"}
{"path": "speaker/Cody_Adams", "name": "Adams, Cody", "letter": "A"}
{"path": "speaker/Colleen_Adams", "name": "Adams, Colleen", "letter": "A"}
{"path": "speaker/Dale_Adams", "name": "Adams, Dale", "letter": "A"}
{"path": "speaker/Daniel_Adams", "name": "Adams, Daniel", "letter": "A"}
{"path": "speaker/David_Adams", "name": "Adams, David", "letter": "A"}
{"path": "speaker/Don_Adams", "name": "Adams, Don", "letter": "A"}
{"path": "speaker/Eric_Adams", "name": "Adams, Eric", "letter": "A"}
{"path": "speaker/Dr._Fred_Adams", "name": "Adams, Fred", "letter": "A"}
{"path": "speaker/Henry_Gregory_Adams", "name": "Adams, Henry Gregory", "letter": "A"}
{"path": "speaker/Dr._James_E._Adams", "name": "Adams, James E.", "letter": "A"}
{"path": "speaker/Dr._Jay_E._Adams", "name": "Adams, Jay E.", "letter": "A"}
{"path": "speaker/Jim_Adams", "name": "Adams, Jim", "letter": "A"}
{"path": "speaker/Joe_Adams", "name": "Adams, Joe", "letter": "A"}
{"path": "speaker/John_Adams", "name": "Adams, John", "letter": "A"}
{"path": "speaker/Josh_Adams", "name": "Adams, Josh", "letter": "A"}
{"path": "speaker/Larry_Adams", "name": "Adams, Larry", "letter": "A"}
{"path": "speaker/Luke_Adams", "name": "Adams, Luke", "letter": "A"}
{"path": "speaker/Mark_Adams", "name": "Adams, Mark", "letter": "A"}
{"path": "speaker/Mike_Adams", "name": "Adams, Mike", "letter": "A"}
{"path": "speaker/Peter_Adams", "name": "Adams, Peter", "letter": "A"}
{"path": "speaker/Phillips_Adams", "name": "Adams, Phillips", "letter": "A"}
{"path": "speaker/Randy_Adams", "name": "Adams, Randy", "letter": "A"}
{"path": "speaker/Richard_Adams", "name": "Adams, Richard", "letter": "A"}
{"path": "speaker/Pastor_Sam_Adams", "name": "Adams, Sam", "letter": "A"}
{"path": "speaker/Mr._Samuel_Adams", "name": "Adams, Samuel", "letter": "A"}
{"path": "speaker/Bro._Stan_Adams", "name": "Adams, Stan", "letter": "A"}
{"path": "speaker/Tim_Adams", "name": "Adams, Tim", "letter": "A"}
{"path": "speaker/Todd_Adams", "name": "Adams, Todd", "letter": "A"}
{"path": "speaker/Paul_Adamsen", "name": "Adamsen, Paul", "letter": "A"}
{"path": "speaker/Brue_Adamson", "name": "Adamson, Brue", "letter": "A"}
{"path": "speaker/Bryce_Adamson", "name": "Adamson, Bryce", "letter": "A"}
{"path": "speaker/Nathaniel_Adawonu", "name": "Adawonu, Nathaniel", "letter": "A"}
{"path": "speaker/Susanna_Adby", "name": "Adby, Susanna", "letter": "A"}
{"path": "speaker/Ryon_Adcock", "name": "Adcock, Ryon", "letter": "A"}
{"path": "speaker/Steve_Adcock", "name": "Adcock, Steve", "letter": "A"}
{"path": "speaker/Brandon_Addison", "name": "Addison, Brandon", "letter": "A"}
{"path": "speaker/Luke_Addison", "name": "Addison, Luke", "letter": "A"}
{"path": "speaker/Seth_Addison", "name": "Addison, Seth", "letter": "A"}
{"path": "speaker/Rick_Aderson", "name": "Aderson, Rick", "letter": "A"}
{"path": "speaker/Albert_Hirak_Adhikari", "name": "Adhikari, Albert Hirak", "letter": "A"}
{"path": "speaker/Dr._Jonathan_Adjabeng", "name": "Adjabeng, Jonathan", "letter": "A"}
{"path": "speaker/Christian_Adjemian", "name": "Adjemian, Christian", "letter": "A"}
{"path": "speaker/Jean-Baptiste_Adjibocha", "name": "Adjibocha, Jean-Baptiste", "letter": "A"}
{"path": "speaker/Dr._Allen_T_Adkins", "name": "Adkins, Allen T", "letter": "A"}
{"path": "speaker/Blake_Adkins", "name": "Adkins, Blake", "letter": "A"}
{"path": "speaker/Brad_Adkins", "name": "Adkins, Brad", "letter": "A"}
{"path": "speaker/Cliff_Adkins", "name": "Adkins, Cliff", "letter": "A"}
{"path": "speaker/Dr._Dale_Adkins", "name": "Adkins, Dale", "letter": "A"}
{"path": "speaker/David_Adkins", "name": "Adkins, David", "letter": "A"}
{"path": "speaker/Ray_Adkins", "name": "Adkins, Ray", "letter": "A"}
{"path": "speaker/Tim_Adkins", "name": "Adkins, Tim", "letter": "A"}
{"path": "speaker/Arnie_Adkinson", "name": "Adkinson, Arnie", "letter": "A"}
{"path": "speaker/Ron_Holton_Arnie_Adkinson", "name": "Adkinson, Ron Holton Arnie", "letter": "A"}
{"path": "speaker/Dr._E._Lewis_Adkison", "name": "Adkison, E. Lewis", "letter": "A"}
{"path": "speaker/Jack_Adlawan", "name": "Adlawan, Jack", "letter": "A"}
{"path": "speaker/James_Admiraal", "name": "Admiraal, James", "letter": "A"}
{"path": "speaker/Scott_Admire", "name": "Admire, Scott", "letter": "A"}
{"path": "speaker/Kofi_Adu-Boahen", "name": "Adu-Boahen, Kofi", "letter": "A"}
{"path": "speaker/Ebenezer_Afful", "name": "Afful, Ebenezer", "letter": "A"}
{"path": "speaker/Dr._Jimmy_Agan", "name": "Agan, Jimmy", "letter": "A"}
{"path": "speaker/Jeff_Agar", "name": "Agar, Jeff", "letter": "A"}
{"path": "speaker/Mrs._Lorri_Agee", "name": "Agee, Lorri", "letter": "A"}
{"path": "speaker/Matt_Agee", "name": "Agee, Matt", "letter": "A"}
{"path": "speaker/D._Agema", "name": "Agema, D.", "letter": "A"}
{"path": "speaker/Doug_Agnew", "name": "Agnew, Doug", "letter": "A"}
{"path": "speaker/Scott_Agnew", "name": "Agnew, Scott", "letter": "A"}
{"path": "speaker/Sean_Agnew", "name": "Agnew, Sean", "letter": "A"}
{"path": "speaker/Jose_Aguero", "name": "Aguero, Jose", "letter": "A"}
{"path": "speaker/Mario_Aguilar", "name": "Aguilar, Mario", "letter": "A"}
{"path": "speaker/Salvador_Aguilar", "name": "Aguilar, Salvador", "letter": "A"}
{"path": "speaker/Obed_Aguirre", "name": "Aguirre, Obed", "letter": "A"}
{"path": "speaker/Joseph_Agyare", "name": "Agyare, Joseph", "letter": "A"}
{"path": "speaker/Stephen_Ahlberg", "name": "Ahlberg, Stephen", "letter": "A"}
{"path": "speaker/Tim_Ahlgrim", "name": "Ahlgrim, Tim", "letter": "A"}
{"path": "speaker/Ishak_Ahmed", "name": "Ahmed, Ishak", "letter": "A"}
{"path": "speaker/Daniel_Ahn", "name": "Ahn, Daniel", "letter": "A"}
{"path": "speaker/Joe_Aho", "name": "Aho, Joe", "letter": "A"}
{"path": "speaker/Dr._Damian_Ahrens", "name": "Ahrens, Damian", "letter": "A"}
{"path": "speaker/Luke_Ahrens", "name": "Ahrens, Luke", "letter": "A"}
{"path": "speaker/Rev._Tom_Aicken", "name": "Aicken, Tom", "letter": "A"}
{"path": "speaker/Christian_Aid", "name": "Aid, Christian", "letter": "A"}
{"path": "speaker/Allen_Aiken", "name": "Aiken, Allen", "letter": "A"}
{"path": "speaker/Melvin_Aiken", "name": "Aiken, Melvin", "letter": "A"}
{"path": "speaker/Peter_Aiken", "name": "Aiken, Peter", "letter": "A"}
{"path": "speaker/Rev_Robert_Aiken", "name": "Aiken, Robert", "letter": "A"}
{"path": "speaker/Tom_Aiken", "name": "Aiken, Tom", "letter": "A"}
{"path": "speaker/Larry_Aikens", "name": "Aikens, Larry", "letter": "A"}
{"path": "speaker/Wilbur_Aikin", "name": "Aikin, Wilbur", "letter": "A"}
{"path": "speaker/David_Aikman", "name": "Aikman, David", "letter": "A"}
{"path": "speaker/Rev._J._Gary_Aitken", "name": "Aitken, J. Gary", "letter": "A"}
{"path": "speaker/Jonathan_Aitken", "name": "Aitken, Jonathan", "letter": "A"}
{"path": "speaker/Glenn_Aittama", "name": "Aittama, Glenn", "letter": "A"}
{"path": "speaker/Ben_Akatsa", "name": "Akatsa, Ben", "letter": "A"}
{"path": "speaker/Mario_Ake", "name": "Ake, Mario", "letter": "A"}
{"path": "speaker/Dave_Akers", "name": "Akers, Dave", "letter": "A"}
{"path": "speaker/Larry_Akers", "name": "Akers, Larry", "letter": "A"}
{"path": "speaker/John_Akeyo", "name": "Akeyo, John", "letter": "A"}
{"path": "speaker/AmyJo_Akin", "name": "Akin, AmyJo", "letter": "A"}
{"path": "speaker/Bob_Akin", "name": "Akin, Bob", "letter": "A"}
{"path": "speaker/Dale_Akin", "name": "Akin, Dale", "letter": "A"}
{"path": "speaker/Dr._Danny_Akin", "name": "Akin, Danny", "letter": "A"}
{"path": "speaker/Jeff_Akin", "name": "Akin, Jeff", "letter": "A"}
{"path": "speaker/Nate_Akin", "name": "Akin, Nate", "letter": "A"}
{"path": "speaker/Bill_Akins", "name": "Akins, Bill", "letter": "A"}
{"path": "speaker/Peter_Akl", "name": "Akl, Peter", "letter": "A"}
{"path": "speaker/Adam_Akre", "name": "Akre, Adam", "letter": "A"}
{"path": "speaker/Gerald_Akrie", "name": "Akrie, Gerald", "letter": "A"}
{"path": "speaker/Missionary_Arnold_Alagao", "name": "Alagao, Arnold", "letter": "A"}
{"path": "speaker/Ibiyinka_Alao", "name": "Alao, Ibiyinka", "letter": "A"}
{"path": "speaker/Phil_Alba_Jr.", "name": "Alba Jr., Phil", "letter": "A"}
{"path": "speaker/Phil_Wayne_Alba_Sr.", "name": "Alba Sr., Phil Wayne", "letter": "A"}
{"path": "speaker/Zachary_Albanese", "name": "Albanese, Zachary", "letter": "A"}
{"path": "speaker/Frank_Albani", "name": "Albani, Frank", "letter": "A"}
{"path": "speaker/Al_Albano", "name": "Albano, Al", "letter": "A"}
{"path": "speaker/John_Albano", "name": "Albano, John", "letter": "A"}
{"path": "speaker/Sara_Albano", "name": "Albano, Sara", "letter": "A"}
{"path": "speaker/John_Albaugh", "name": "Albaugh, John", "letter": "A"}
{"path": "speaker/Tom_Albaugh", "name": "Albaugh, Tom", "letter": "A"}
{"path": "speaker/Troy_Albee", "name": "Albee, Troy", "letter": "A"}
{"path": "speaker/Sam_Alberry", "name": "Alberry, Sam", "letter": "A"}
{"path": "speaker/Brian_Albert", "name": "Albert, Brian", "letter": "A"}
{"path": "speaker/Kevin_Albert", "name": "Albert, Kevin", "letter": "A"}
{"path": "speaker/Patty_Albert", "name": "Albert, Patty", "letter": "A"}
{"path": "speaker/Diana_Alblas", "name": "Alblas, Diana", "letter": "A"}
{"path": "speaker/Donald_Albright", "name": "Albright, Donald", "letter": "A"}
{"path": "speaker/Greg_Albright", "name": "Albright, Greg", "letter": "A"}
{"path": "speaker/Pastor_Joel_Albright", "name": "Albright, Joel", "letter": "A"}
{"path": "speaker/Stephen_Albright", "name": "Albright, Stephen", "letter": "A"}
{"path": "speaker/Rodolfo_Alburto", "name": "Alburto, Rodolfo", "letter": "A"}
{"path": "speaker/Richard_Albury", "name": "Albury, Richard", "letter": "A"}
{"path": "speaker/Rafael_Alc\u00e1ntara", "name": "Alc\u00e1ntara, Rafael", "letter": "A"}
{"path": "speaker/Jonty_Alcock", "name": "Alcock, Jonty", "letter": "A"}
{"path": "speaker/Mark_Alcock", "name": "Alcock, Mark", "letter": "A"}
{"path": "speaker/Brent_Alderman", "name": "Alderman, Brent", "letter": "A"}
{"path": "speaker/Dr._Robert_L._Alderman", "name": "Alderman, Robert L.", "letter": "A"}
{"path": "speaker/Al_Aldrich", "name": "Aldrich, Al", "letter": "A"}
{"path": "speaker/Joseph_Aldrich", "name": "Aldrich, Joseph", "letter": "A"}
{"path": "speaker/Rick_Aldrich_-_Elder", "name": "Aldrich, Rick", "letter": "A"}
{"path": "speaker/Ryan_Aldrich", "name": "Aldrich, Ryan", "letter": "A"}
{"path": "speaker/Tad_Aldrich", "name": "Aldrich, Tad", "letter": "A"}
{"path": "speaker/Bobby_Aldridge", "name": "Aldridge, Bobby", "letter": "A"}
{"path": "speaker/Eric_Aldritt", "name": "Aldritt, Eric", "letter": "A"}
{"path": "speaker/Pastor_Alan_Alemada", "name": "Alemada, Alan", "letter": "A"}
{"path": "speaker/Shawn_Alexander,_Jr.", "name": "Alexander Jr, Shawn", "letter": "A"}
{"path": "speaker/Archibald_Alexander", "name": "Alexander, Archibald", "letter": "A"}
{"path": "speaker/Ben_Alexander", "name": "Alexander, Ben", "letter": "A"}
{"path": "speaker/Bob_Alexander", "name": "Alexander, Bob", "letter": "A"}
{"path": "speaker/Brian_Alexander", "name": "Alexander, Brian", "letter": "A"}
{"path": "speaker/Charles_Alexander", "name": "Alexander, Charles", "letter": "A"}
{"path": "speaker/Charles_M._Alexander", "name": "Alexander, Charles M.", "letter": "A"}
{"path": "speaker/Clayton_Alexander", "name": "Alexander, Clayton", "letter": "A"}
{"path": "speaker/David_Alexander", "name": "Alexander, David", "letter": "A"}
{"path": "speaker/David_C._Alexander", "name": "Alexander, David C.", "letter": "A"}
{"path": "speaker/Ed_Alexander", "name": "Alexander, Ed", "letter": "A"}
{"path": "speaker/Rev._Eric_Alexander", "name": "Alexander, Eric", "letter": "A"}
{"path": "speaker/James_Alexander", "name": "Alexander, James", "letter": "A"}
{"path": "speaker/James_J._Alexander", "name": "Alexander, James J.", "letter": "A"}
{"path": "speaker/James_W._Alexander", "name": "Alexander, James W.", "letter": "A"}
{"path": "speaker/Jeffrey_Alexander", "name": "Alexander, Jeffrey", "letter": "A"}
{"path": "speaker/Kirk_Alexander", "name": "Alexander, Kirk", "letter": "A"}
{"path": "speaker/Mark_Alexander", "name": "Alexander, Mark", "letter": "A"}
{"path": "speaker/Paul_Alexander", "name": "Alexander, Paul", "letter": "A"}
{"path": "speaker/Paul_M._Alexander", "name": "Alexander, Paul M.", "letter": "A"}
{"path": "speaker/PJ_Alexander", "name": "Alexander, PJ", "letter": "A"}
{"path": "speaker/Robbie_Alexander", "name": "Alexander, Robbie", "letter": "A"}
{"path": "speaker/Shawn_Alexander", "name": "Alexander, Shawn", "letter": "A"}
{"path": "speaker/Ted_Alexander", "name": "Alexander, Ted", "letter": "A"}
{"path": "speaker/Nikolai_Alexandrenko", "name": "Alexandrenko, Nikolai", "letter": "A"}
{"path": "speaker/Michael_Alexandrov", "name": "Alexandrov, Michael", "letter": "A"}
{"path": "speaker/Andy_Alexson", "name": "Alexson, Andy", "letter": "A"}
{"path": "speaker/Bacillo_Alfaro", "name": "Alfaro, Bacillo", "letter": "A"}
{"path": "speaker/Basilio_Alfaro", "name": "Alfaro, Basilio", "letter": "A"}
{"path": "speaker/Miguel_Alfaro", "name": "Alfaro, Miguel", "letter": "A"}
{"path": "speaker/Aris_Alfonso", "name": "Alfonso, Aris", "letter": "A"}
{"path": "speaker/Michael_Alford", "name": "Alford, Michael", "letter": "A"}
{"path": "speaker/Bro._Mike_Alford", "name": "Alford, Mike", "letter": "A"}
{"path": "speaker/Nick_Alford", "name": "Alford, Nick", "letter": "A"}
{"path": "speaker/Owen_Alford", "name": "Alford, Owen", "letter": "A"}
{"path": "speaker/Pat_Alford", "name": "Alford, Pat", "letter": "A"}
{"path": "speaker/Roger_Alford", "name": "Alford, Roger", "letter": "A"}
{"path": "speaker/Timothy_Alford", "name": "Alford, Timothy", "letter": "A"}
{"path": "speaker/Wes_Alford", "name": "Alford, Wes", "letter": "A"}
{"path": "speaker/Joseph_Alghrary", "name": "Alghrary, Joseph", "letter": "A"}
{"path": "speaker/Sergio_Ali", "name": "Ali, Sergio", "letter": "A"}
{"path": "speaker/Pepe_Alicea", "name": "Alicea, Pepe", "letter": "A"}
{"path": "speaker/Eddy_Aliff", "name": "Aliff, Eddy", "letter": "A"}
{"path": "speaker/Rene_Alincastre", "name": "Alincastre, Rene", "letter": "A"}
{"path": "speaker/H._Alkema", "name": "Alkema, H.", "letter": "A"}
{"path": "speaker/Stan_Allaby", "name": "Allaby, Stan", "letter": "A"}
{"path": "speaker/Brent_Allamon", "name": "Allamon, Brent", "letter": "A"}
{"path": "speaker/Mark_Allamon", "name": "Allamon, Mark", "letter": "A"}
{"path": "speaker/Andrew_R_Allan", "name": "Allan, Andrew R", "letter": "A"}
{"path": "speaker/Austin_Allan", "name": "Allan, Austin", "letter": "A"}
{"path": "speaker/Blake_Allan", "name": "Allan, Blake", "letter": "A"}
{"path": "speaker/Billy_Allardice", "name": "Allardice, Billy", "letter": "A"}
{"path": "speaker/Rob_Allas", "name": "Allas, Rob", "letter": "A"}
{"path": "speaker/Rev._James_Allay", "name": "Allay, James", "letter": "A"}
{"path": "speaker/Loren_Allbaugh", "name": "Allbaugh, Loren", "letter": "A"}
{"path": "speaker/Sam_Allberry", "name": "Allberry, Sam", "letter": "A"}
{"path": "speaker/Eric_J._Alldritt", "name": "Alldritt, Eric J.", "letter": "A"}
{"path": "speaker/Reverend_Jarrett_Allebach", "name": "Allebach, Jarrett", "letter": "A"}
{"path": "speaker/Jacob_Allee", "name": "Allee, Jacob", "letter": "A"}
{"path": "speaker/Joseph_Alleine", "name": "Alleine, Joseph", "letter": "A"}
{"path": "speaker/Richard_Alleine", "name": "Alleine, Richard", "letter": "A"}
{"path": "speaker/Clifford_Allen,_Jr.", "name": "Allen Jr, Clifford", "letter": "A"}
{"path": "speaker/Rev._Austin_Allen", "name": "Allen, Austin", "letter": "A"}
{"path": "speaker/Billy_Allen", "name": "Allen, Billy", "letter": "A"}
{"path": "speaker/Bob_Allen", "name": "Allen, Bob", "letter": "A"}
{"path": "speaker/Bruce_Allen", "name": "Allen, Bruce", "letter": "A"}
{"path": "speaker/Caleb_Allen", "name": "Allen, Caleb", "letter": "A"}
{"path": "speaker/Caleb_S_Allen", "name": "Allen, Caleb S", "letter": "A"}
{"path": "speaker/Dale_Allen", "name": "Allen, Dale", "letter": "A"}
{"path": "speaker/Dr._David_Allen_UK", "name": "Allen, David (UK)", "letter": "A"}
{"path": "speaker/David_L._Allen", "name": "Allen, David L.", "letter": "A"}
{"path": "speaker/David_T._Allen", "name": "Allen, David T.", "letter": "A"}
{"path": "speaker/Dean_Allen", "name": "Allen, Dean", "letter": "A"}
{"path": "speaker/Flay_Allen", "name": "Allen, Flay", "letter": "A"}
{"path": "speaker/Gary_Allen", "name": "Allen, Gary", "letter": "A"}
{"path": "speaker/Rev._Geoffrey_Allen", "name": "Allen, Geoffrey", "letter": "A"}
{"path": "speaker/Horace_Allen", "name": "Allen, Horace", "letter": "A"}
{"path": "speaker/Ian_Allen", "name": "Allen, Ian", "letter": "A"}
{"path": "speaker/Jaden_Allen", "name": "Allen, Jaden", "letter": "A"}
{"path": "speaker/James_Allen", "name": "Allen, James", "letter": "A"}
{"path": "speaker/Jamie_Allen", "name": "Allen, Jamie", "letter": "A"}
{"path": "speaker/Dr._Jason_Allen", "name": "Allen, Jason", "letter": "A"}
{"path": "speaker/Jeff_Allen", "name": "Allen, Jeff", "letter": "A"}
{"path": "speaker/Joe_W_Allen", "name": "Allen, Joe W", "letter": "A"}
{"path": "speaker/John_Allen", "name": "Allen, John", "letter": "A"}
{"path": "speaker/Jordan_Allen", "name": "Allen, Jordan", "letter": "A"}
{"path": "speaker/Joseph_Allen", "name": "Allen, Joseph", "letter": "A"}
{"path": "speaker/Keith_Allen", "name": "Allen, Keith", "letter": "A"}
{"path": "speaker/Kevin_Allen", "name": "Allen, Kevin", "letter": "A"}
{"path": "speaker/Kyle_Allen", "name": "Allen, Kyle", "letter": "A"}
{"path": "speaker/Lindsay_Allen", "name": "Allen, Lindsay", "letter": "A"}
{"path": "speaker/Rev_Martin_Allen", "name": "Allen, Martin", "letter": "A"}
{"path": "speaker/Matt_Allen", "name": "Allen, Matt", "letter": "A"}
{"path": "speaker/Michael_Allen", "name": "Allen, Michael", "letter": "A"}
{"path": "speaker/Michael_L._Allen", "name": "Allen, Michael L.", "letter": "A"}
{"path": "speaker/Mike_Allen", "name": "Allen, Mike", "letter": "A"}
{"path": "speaker/Nathan_Allen", "name": "Allen, Nathan", "letter": "A"}
{"path": "speaker/Rachel_Allen", "name": "Allen, Rachel", "letter": "A"}
{"path": "speaker/Dr._Ron_Allen", "name": "Allen, Ron", "letter": "A"}
{"path": "speaker/Ron_Allen_(Canton,_GA)", "name": "Allen, Ron (Canton, GA)", "letter": "A"}
{"path": "speaker/Ryan_Allen", "name": "Allen, Ryan", "letter": "A"}
{"path": "speaker/Sammy_Allen", "name": "Allen, Sammy", "letter": "A"}
{"path": "speaker/Scott_Allen", "name": "Allen, Scott", "letter": "A"}
{"path": "speaker/Spencer_Allen", "name": "Allen, Spencer", "letter": "A"}
{"path": "speaker/Steve_Allen", "name": "Allen, Steve", "letter": "A"}
{"path": "speaker/Todd_W._Allen", "name": "Allen, Todd W.", "letter": "A"}
{"path": "speaker/Tom_Allen", "name": "Allen, Tom", "letter": "A"}
{"path": "speaker/Travis_Allen", "name": "Allen, Travis", "letter": "A"}
{"path": "speaker/Wade_Allen", "name": "Allen, Wade", "letter": "A"}
{"path": "speaker/Walter_Allen", "name": "Allen, Walter", "letter": "A"}
{"path": "speaker/Adam_Alley", "name": "Alley, Adam", "letter": "A"}
{"path": "speaker/James_Alley", "name": "Alley, James", "letter": "A"}
{"path": "speaker/Dr._Jim_Alley", "name": "Alley, Jim", "letter": "A"}
{"path": "speaker/Rev._John_Allgaier", "name": "Allgaier, John", "letter": "A"}
{"path": "speaker/Tolani_Alli", "name": "Alli, Tolani", "letter": "A"}
{"path": "speaker/Thomas_Allie", "name": "Allie, Thomas", "letter": "A"}
{"path": "speaker/Charles_Alligood", "name": "Alligood, Charles", "letter": "A"}
{"path": "speaker/Archibald_A._Allison", "name": "Allison, Archibald A.", "letter": "A"}
{"path": "speaker/Jeff_Allison", "name": "Allison, Jeff", "letter": "A"}
{"path": "speaker/Jon_Allison", "name": "Allison, Jon", "letter": "A"}
{"path": "speaker/Keith_Allison", "name": "Allison, Keith", "letter": "A"}
{"path": "speaker/Mark_Allison", "name": "Allison, Mark", "letter": "A"}
{"path": "speaker/Mike_Allison", "name": "Allison, Mike", "letter": "A"}
{"path": "speaker/Pastor_Sam_M._Allison", "name": "Allison, Sam M.", "letter": "A"}
{"path": "speaker/Stephen_Allison", "name": "Allison, Stephen", "letter": "A"}
{"path": "speaker/Dr._Jim_Allman", "name": "Allman, Jim", "letter": "A"}
{"path": "speaker/Oliver_Allmand-Smith", "name": "Allmand-Smith, Oliver", "letter": "A"}
{"path": "speaker/Rev._Brian_Allred", "name": "Allred, Brian", "letter": "A"}
{"path": "speaker/John_Alls", "name": "Alls, John", "letter": "A"}
{"path": "speaker/Glen_Allshouse", "name": "Allshouse, Glen", "letter": "A"}
{"path": "speaker/Ben_Allston", "name": "Allston, Ben", "letter": "A"}
{"path": "speaker/Ted_Allston", "name": "Allston, Ted", "letter": "A"}
{"path": "speaker/Travis_Alltop", "name": "Alltop, Travis", "letter": "A"}
{"path": "speaker/Bob_Allums", "name": "Allums, Bob", "letter": "A"}
{"path": "speaker/Tim_Allums", "name": "Allums, Tim", "letter": "A"}
{"path": "speaker/Joe_Allyn", "name": "Allyn, Joe", "letter": "A"}
{"path": "speaker/Tom_Almanza", "name": "Almanza, Tom", "letter": "A"}
{"path": "speaker/Cody_Almanzar", "name": "Almanzar, Cody", "letter": "A"}
{"path": "speaker/Miguel_Alm\u00e1nzar", "name": "Alm\u00e1nzar, Miguel", "letter": "A"}
{"path": "speaker/Clelia_Almeida", "name": "Almeida, Clelia", "letter": "A"}
{"path": "speaker/Pedro_Almeida", "name": "Almeida, Pedro", "letter": "A"}
{"path": "speaker/Jarrod_Almond", "name": "Almond, Jarrod", "letter": "A"}
{"path": "speaker/Logan_Almy", "name": "Almy, Logan", "letter": "A"}
{"path": "speaker/Rev._Nick_Alons", "name": "Alons, Nick", "letter": "A"}
{"path": "speaker/Tico_Alonso", "name": "Alonso, Tico", "letter": "A"}
{"path": "speaker/Rev._Valent\u00edn_Alpuche", "name": "Alpuche, Valent\u00edn", "letter": "A"}
{"path": "speaker/John_Alsop", "name": "Alsop, John", "letter": "A"}
{"path": "speaker/Randy_Alston", "name": "Alston, Randy", "letter": "A"}
{"path": "speaker/Erik_van_Alten", "name": "Alten, Erik van", "letter": "A"}
{"path": "speaker/Sigay_Alt\u00e9on", "name": "Alt\u00e9on, Sigay", "letter": "A"}
{"path": "speaker/Jerrell_Altic", "name": "Altic, Jerrell", "letter": "A"}
{"path": "speaker/Guy_Altizer", "name": "Altizer, Guy", "letter": "A"}
{"path": "speaker/Rick_Altizer", "name": "Altizer, Rick", "letter": "A"}
{"path": "speaker/Blake_Altman", "name": "Altman, Blake", "letter": "A"}
{"path": "speaker/Richard_Altman", "name": "Altman, Richard", "letter": "A"}
{"path": "speaker/Rev._Steven_Altman", "name": "Altman, Steven", "letter": "A"}
{"path": "speaker/George_Alvarado", "name": "Alvarado, George", "letter": "A"}
{"path": "speaker/Rev._Angel_Alvarez", "name": "Alvarez, Angel", "letter": "A"}
{"path": "speaker/Arthur_Alvarez", "name": "Alvarez, Arthur", "letter": "A"}
{"path": "speaker/Carlos_Alvarez", "name": "Alvarez, Carlos", "letter": "A"}
{"path": "speaker/Pastor_Daniel_Alvarez", "name": "Alvarez, Daniel", "letter": "A"}
{"path": "speaker/Fermin_Alvarez", "name": "Alvarez, Fermin", "letter": "A"}
{"path": "speaker/Israel_Alvarez", "name": "Alvarez, Israel", "letter": "A"}
{"path": "speaker/Jose_Alvarez", "name": "Alvarez, Jose", "letter": "A"}
{"path": "speaker/Kody_Alvarez", "name": "Alvarez, Kody", "letter": "A"}
{"path": "speaker/Steven_Alvarez", "name": "Alvarez, Steven", "letter": "A"}
{"path": "speaker/Pastor_Victor_Alvarez", "name": "Alvarez, Victor", "letter": "A"}
{"path": "speaker/Jeff_Alverson", "name": "Alverson, Jeff", "letter": "A"}
{"path": "speaker/Ben_Alvira", "name": "Alvira, Ben", "letter": "A"}
{"path": "speaker/Tony_Alvira", "name": "Alvira, Tony", "letter": "A"}
{"path": "speaker/Darin_Alvis", "name": "Alvis, Darin", "letter": "A"}
{"path": "speaker/Bruce_Alvord", "name": "Alvord, Bruce", "letter": "A"}
{"path": "speaker/Scott_Alwine", "name": "Alwine, Scott", "letter": "A"}
{"path": "speaker/Kelly_Amador", "name": "Amador, Kelly", "letter": "A"}
{"path": "speaker/Richard_Amador", "name": "Amador, Richard", "letter": "A"}
{"path": "speaker/Phil_Amaismeier", "name": "Amaismeier, Phil", "letter": "A"}
{"path": "speaker/Ralph_Amateis", "name": "Amateis, Ralph", "letter": "A"}
{"path": "speaker/Isaac_Ambrose", "name": "Ambrose, Isaac", "letter": "A"}
{"path": "speaker/Derek_Ambrosen", "name": "Ambrosen, Derek", "letter": "A"}
{"path": "speaker/Brian_Amburgey", "name": "Amburgey, Brian", "letter": "A"}
{"path": "speaker/Kevin_Amburgey", "name": "Amburgey, Kevin", "letter": "A"}
{"path": "speaker/Chris_Ames", "name": "Ames, Chris", "letter": "A"}
{"path": "speaker/Stuart_Amidon", "name": "Amidon, Stuart", "letter": "A"}
{"path": "speaker/Mike_Amira", "name": "Amira, Mike", "letter": "A"}
{"path": "speaker/Rev._Robert_Amon", "name": "Amon, Robert", "letter": "A"}
{"path": "speaker/Andres_Amoros", "name": "Amoros, Andres", "letter": "A"}
{"path": "speaker/Bobby_Amos", "name": "Amos, Bobby", "letter": "A"}
{"path": "speaker/Dr._Jeff_Amsbaugh", "name": "Amsbaugh, Jeff", "letter": "A"}
{"path": "speaker/Rob_Amsler", "name": "Amsler, Rob", "letter": "A"}
{"path": "speaker/Jeremy_Amster", "name": "Amster, Jeremy", "letter": "A"}
{"path": "speaker/Bill_Amstutz", "name": "Amstutz, Bill", "letter": "A"}
{"path": "speaker/Ernie_Amurao", "name": "Amurao, Ernie", "letter": "A"}
{"path": "speaker/Kyle_Amyx", "name": "Amyx, Kyle", "letter": "A"}
{"path": "speaker/Joe_Anady", "name": "Anady, Joe", "letter": "A"}
{"path": "speaker/Phil_Anady", "name": "Anady, Phil", "letter": "A"}
{"path": "speaker/Erskin_Anavitarte", "name": "Anavitarte, Erskin", "letter": "A"}
{"path": "speaker/Josh_Ancello", "name": "Ancello, Josh", "letter": "A"}
{"path": "speaker/Dimver_Andales", "name": "Andales, Dimver", "letter": "A"}
{"path": "speaker/Ralph_Anderegg", "name": "Anderegg, Ralph", "letter": "A"}
{"path": "speaker/Andy_Anders", "name": "Anders, Andy", "letter": "A"}
{"path": "speaker/Matthew_Anders", "name": "Anders, Matthew", "letter": "A"}
{"path": "speaker/David_Andersen", "name": "Andersen, David", "letter": "A"}
{"path": "speaker/Dr._David_C._Andersen", "name": "Andersen, David C.", "letter": "A"}
{"path": "speaker/R._Wayne_Andersen", "name": "Andersen, R. Wayne", "letter": "A"}
{"path": "speaker/Dr._Ward_Andersen", "name": "Andersen, Ward", "letter": "A"}
{"path": "speaker/Bill_Anderson", "name": "Anderson, Bill", "letter": "A"}
{"path": "speaker/Brad_Anderson", "name": "Anderson, Brad", "letter": "A"}
{"path": "speaker/Bradley_Anderson", "name": "Anderson, Bradley", "letter": "A"}
{"path": "speaker/Brian_Anderson", "name": "Anderson, Brian", "letter": "A"}
{"path": "speaker/Charles_Anderson", "name": "Anderson, Charles", "letter": "A"}
{"path": "speaker/Charles_E._Anderson", "name": "Anderson, Charles E.", "letter": "A"}
{"path": "speaker/Chris_Anderson", "name": "Anderson, Chris", "letter": "A"}
{"path": "speaker/Christopher_M._Anderson", "name": "Anderson, Christopher M.", "letter": "A"}
{"path": "speaker/Christopher_S._Anderson", "name": "Anderson, Christopher S.", "letter": "A"}
{"path": "speaker/Chuck_Anderson", "name": "Anderson, Chuck", "letter": "A"}
{"path": "speaker/Cody_Anderson", "name": "Anderson, Cody", "letter": "A"}
{"path": "speaker/Craig_Anderson", "name": "Anderson, Craig", "letter": "A"}
{"path": "speaker/Dale_Anderson", "name": "Anderson, Dale", "letter": "A"}
{"path": "speaker/Dan_Anderson", "name": "Anderson, Dan", "letter": "A"}
{"path": "speaker/Daniel_Anderson", "name": "Anderson, Daniel", "letter": "A"}
{"path": "speaker/Dave_Anderson", "name": "Anderson, Dave", "letter": "A"}
{"path": "speaker/David_Anderson", "name": "Anderson, David", "letter": "A"}
{"path": "speaker/Rev._David_Anderson_(FPC)", "name": "Anderson, David (FPC)", "letter": "A"}
{"path": "speaker/David_C._Anderson", "name": "Anderson, David C.", "letter": "A"}
{"path": "speaker/David_W._Anderson", "name": "Anderson, David W.", "letter": "A"}
{"path": "speaker/Dr._Don_Anderson", "name": "Anderson, Don", "letter": "A"}
{"path": "speaker/Pastor_Ed_Anderson", "name": "Anderson, Ed", "letter": "A"}
{"path": "speaker/Eric_Anderson", "name": "Anderson, Eric", "letter": "A"}
{"path": "speaker/Gary_Anderson", "name": "Anderson, Gary", "letter": "A"}
{"path": "speaker/George_Anderson", "name": "Anderson, George", "letter": "A"}
{"path": "speaker/Graham_Anderson", "name": "Anderson, Graham", "letter": "A"}
{"path": "speaker/Gregg_Anderson", "name": "Anderson, Gregg", "letter": "A"}
{"path": "speaker/Bro._Hank_Anderson", "name": "Anderson, Hank", "letter": "A"}
{"path": "speaker/Dr._J._Kent_Anderson", "name": "Anderson, J. Kent", "letter": "A"}
{"path": "speaker/James_Anderson", "name": "Anderson, James", "letter": "A"}
{"path": "speaker/James_C._Anderson", "name": "Anderson, James C.", "letter": "A"}
{"path": "speaker/Jason_Anderson", "name": "Anderson, Jason", "letter": "A"}
{"path": "speaker/Jeff_Anderson", "name": "Anderson, Jeff", "letter": "A"}
{"path": "speaker/Jeff_(Missionary)_Anderson", "name": "Anderson, Jeff (Missionary)", "letter": "A"}
{"path": "speaker/Jerry_Anderson", "name": "Anderson, Jerry", "letter": "A"}
{"path": "speaker/Jesse_Anderson", "name": "Anderson, Jesse", "letter": "A"}
{"path": "speaker/Dr._Jim_Anderson", "name": "Anderson, Jim", "letter": "A"}
{"path": "speaker/John_Anderson", "name": "Anderson, John", "letter": "A"}
{"path": "speaker/John_M._Anderson", "name": "Anderson, John M.", "letter": "A"}
{"path": "speaker/Jonathan_Anderson", "name": "Anderson, Jonathan", "letter": "A"}
{"path": "speaker/Josh_Anderson", "name": "Anderson, Josh", "letter": "A"}
{"path": "speaker/Kenny_Anderson", "name": "Anderson, Kenny", "letter": "A"}
{"path": "speaker/Lars_Anderson", "name": "Anderson, Lars", "letter": "A"}
{"path": "speaker/Luke_Anderson", "name": "Anderson, Luke", "letter": "A"}
{"path": "speaker/Matt_Anderson", "name": "Anderson, Matt", "letter": "A"}
{"path": "speaker/Nathan_Anderson", "name": "Anderson, Nathan", "letter": "A"}
{"path": "speaker/Nick_Anderson", "name": "Anderson, Nick", "letter": "A"}
{"path": "speaker/Patrick_Anderson", "name": "Anderson, Patrick", "letter": "A"}
{"path": "speaker/Paul_Anderson", "name": "Anderson, Paul", "letter": "A"}
{"path": "speaker/Paul_D._Anderson", "name": "Anderson, Paul D.", "letter": "A"}
{"path": "speaker/Paul_H._Anderson", "name": "Anderson, Paul H.", "letter": "A"}
{"path": "speaker/Peter_Anderson", "name": "Anderson, Peter", "letter": "A"}
{"path": "speaker/Randy_Anderson", "name": "Anderson, Randy", "letter": "A"}
{"path": "speaker/Raymond_Anderson", "name": "Anderson, Raymond", "letter": "A"}
{"path": "speaker/Richard_Anderson", "name": "Anderson, Richard", "letter": "A"}
{"path": "speaker/Richard_S._Anderson", "name": "Anderson, Richard S.", "letter": "A"}
{"path": "speaker/Rick_Anderson", "name": "Anderson, Rick", "letter": "A"}
{"path": "speaker/Dr._Robert_Anderson", "name": "Anderson, Robert", "letter": "A"}
{"path": "speaker/Rev_Dr_Roger_Dean_Anderson", "name": "Anderson, Roger Dean", "letter": "A"}
{"path": "speaker/Ron_Anderson", "name": "Anderson, Ron", "letter": "A"}
{"path": "speaker/Scott_Anderson", "name": "Anderson, Scott", "letter": "A"}
{"path": "speaker/Scott_C._Anderson", "name": "Anderson, Scott C.", "letter": "A"}
{"path": "speaker/Scotty_S._Anderson", "name": "Anderson, Scotty S.", "letter": "A"}
{"path": "speaker/Shawn_Anderson", "name": "Anderson, Shawn", "letter": "A"}
{"path": "speaker/Sidney_Anderson", "name": "Anderson, Sidney", "letter": "A"}
{"path": "speaker/Mr_Simon_Anderson", "name": "Anderson, Simon", "letter": "A"}
{"path": "speaker/Dr._Stan_Anderson", "name": "Anderson, Stan", "letter": "A"}
{"path": "speaker/Stephen_Anderson", "name": "Anderson, Stephen", "letter": "A"}
{"path": "speaker/Stephen_B._Anderson", "name": "Anderson, Stephen B.", "letter": "A"}
{"path": "speaker/Steve_Anderson", "name": "Anderson, Steve", "letter": "A"}
{"path": "speaker/Sydney_Anderson", "name": "Anderson, Sydney", "letter": "A"}
{"path": "speaker/Thomas_J_Anderson", "name": "Anderson, Thomas J", "letter": "A"}
{"path": "speaker/Mr_Tommy_Anderson", "name": "Anderson, Tommy", "letter": "A"}
{"path": "speaker/Troy_Anderson", "name": "Anderson, Troy", "letter": "A"}
{"path": "speaker/Elder_William_Anderson", "name": "Anderson, William", "letter": "A"}
{"path": "speaker/Zachary_Anderson", "name": "Anderson, Zachary", "letter": "A"}
{"path": "speaker/Paul_Anderson-Walsh", "name": "Anderson-Walsh, Paul", "letter": "A"}
{"path": "speaker/Eric_Andrade", "name": "Andrade, Eric", "letter": "A"}
{"path": "speaker/Steve_Andras", "name": "Andras, Steve", "letter": "A"}
{"path": "speaker/Will_Andras", "name": "Andras, Will", "letter": "A"}
{"path": "speaker/Robert_Andrejczyk", "name": "Andrejczyk, Robert", "letter": "A"}
{"path": "speaker/Lawrence_Andres", "name": "Andres, Lawrence", "letter": "A"}
{"path": "speaker/Anderson_Andrevil", "name": "Andrevil, Anderson", "letter": "A"}
{"path": "speaker/Josh_Andrew", "name": "Andrew, Josh", "letter": "A"}
{"path": "speaker/Ben_Andrews", "name": "Andrews, Ben", "letter": "A"}
{"path": "speaker/Billy_Andrews", "name": "Andrews, Billy", "letter": "A"}
{"path": "speaker/Bo_Andrews", "name": "Andrews, Bo", "letter": "A"}
{"path": "speaker/Brett_Andrews", "name": "Andrews, Brett", "letter": "A"}
{"path": "speaker/Caleb_Andrews", "name": "Andrews, Caleb", "letter": "A"}
{"path": "speaker/Cecil_Andrews", "name": "Andrews, Cecil", "letter": "A"}
{"path": "speaker/Cedric_Andrews", "name": "Andrews, Cedric", "letter": "A"}
{"path": "speaker/Charles_Andrews", "name": "Andrews, Charles", "letter": "A"}
{"path": "speaker/David_Andrews", "name": "Andrews, David", "letter": "A"}
{"path": "speaker/Dennis_Andrews", "name": "Andrews, Dennis", "letter": "A"}
{"path": "speaker/Jim_Andrews", "name": "Andrews, Jim", "letter": "A"}
{"path": "speaker/John_Andrews", "name": "Andrews, John", "letter": "A"}
{"path": "speaker/John_D._Andrews", "name": "Andrews, John D.", "letter": "A"}
{"path": "speaker/Jonathan_D._Andrews", "name": "Andrews, Jonathan D.", "letter": "A"}
{"path": "speaker/Ken_Andrews", "name": "Andrews, Ken", "letter": "A"}
{"path": "speaker/Rev._Lacy_Andrews", "name": "Andrews, Lacy", "letter": "A"}
{"path": "speaker/Mike_Andrews", "name": "Andrews, Mike", "letter": "A"}
{"path": "speaker/Nick_Andrews", "name": "Andrews, Nick", "letter": "A"}
{"path": "speaker/Peter_Andrews", "name": "Andrews, Peter", "letter": "A"}
{"path": "speaker/Reddit_Andrews", "name": "Andrews, Reddit", "letter": "A"}
{"path": "speaker/Rex_Andrews", "name": "Andrews, Rex", "letter": "A"}
{"path": "speaker/Rich_Andrews", "name": "Andrews, Rich", "letter": "A"}
{"path": "speaker/Richard_Andrews", "name": "Andrews, Richard", "letter": "A"}
{"path": "speaker/Rob_Andrews", "name": "Andrews, Rob", "letter": "A"}
{"path": "speaker/Robert_Andrews", "name": "Andrews, Robert", "letter": "A"}
{"path": "speaker/Tim_Andrews", "name": "Andrews, Tim", "letter": "A"}
{"path": "speaker/Jim_Andruss", "name": "Andruss, Jim", "letter": "A"}
{"path": "speaker/Michael_Andrzejewski", "name": "Andrzejewski, Michael", "letter": "A"}
{"path": "speaker/Rev._Ken_Anema", "name": "Anema, Ken", "letter": "A"}
{"path": "speaker/Nate_Ange", "name": "Ange, Nate", "letter": "A"}
{"path": "speaker/Teddy_Angel", "name": "Angel, Teddy", "letter": "A"}
{"path": "speaker/John_Angelerie", "name": "Angelerie, John", "letter": "A"}
{"path": "speaker/Bro_Gilbert_Anger", "name": "Anger, Gilbert", "letter": "A"}
{"path": "speaker/Thomas_Anger", "name": "Anger, Thomas", "letter": "A"}
{"path": "speaker/Mark_Angerosa", "name": "Angerosa, Mark", "letter": "A"}
{"path": "speaker/Ben_Anglea", "name": "Anglea, Ben", "letter": "A"}
{"path": "speaker/Joy_Anglea", "name": "Anglea, Joy", "letter": "A"}
{"path": "speaker/Pastor_Terry_Anglea", "name": "Anglea, Terry", "letter": "A"}
{"path": "speaker/Micah_Anglo", "name": "Anglo, Micah", "letter": "A"}
{"path": "speaker/Ted_Angrove", "name": "Angrove, Ted", "letter": "A"}
{"path": "speaker/Tom_Angstead", "name": "Angstead, Tom", "letter": "A"}
{"path": "speaker/George_Anibaba", "name": "Anibaba, George", "letter": "A"}
{"path": "speaker/Scott_Aniol", "name": "Aniol, Scott", "letter": "A"}
{"path": "speaker/Rev._Anjema", "name": "Anjema", "letter": "A"}
{"path": "speaker/Rich_Anjema", "name": "Anjema, Rich", "letter": "A"}
{"path": "speaker/Richard_Anjema", "name": "Anjema, Richard", "letter": "A"}
{"path": "speaker/Mike_Ankin", "name": "Ankin, Mike", "letter": "A"}
{"path": "speaker/Christian_Ankrom", "name": "Ankrom, Christian", "letter": "A"}
{"path": "speaker/Earl_Ankrom", "name": "Ankrom, Earl", "letter": "A"}
{"path": "speaker/Anna", "name": "Anna", "letter": "A"}
{"path": "speaker/Samuel_Annesley", "name": "Annesley, Samuel", "letter": "A"}
{"path": "speaker/William_Annette", "name": "Annette, William", "letter": "A"}
{"path": "speaker/Pastor_Paul_Anobile", "name": "Anobile, Paul", "letter": "A"}
{"path": "speaker/Anonymous", "name": "Anonymous", "letter": "A"}
{"path": "speaker/Miller_Ansell", "name": "Ansell, Miller", "letter": "A"}
{"path": "speaker/Yves_Anselme", "name": "Anselme, Yves", "letter": "A"}
{"path": "speaker/Nathan_Anseth", "name": "Anseth, Nathan", "letter": "A"}
{"path": "speaker/Jason_Anspach", "name": "Anspach, Jason", "letter": "A"}
{"path": "speaker/John_Warren_Antalika", "name": "Antalika, John Warren", "letter": "A"}
{"path": "speaker/Paul_Anthes", "name": "Anthes, Paul", "letter": "A"}
{"path": "speaker/Rev._Leonard_C._Anthony", "name": "Anthony, Leonard C.", "letter": "A"}
{"path": "speaker/Mbanongon-Kurugh_Antiev", "name": "Antiev, Mbanongon-Kurugh", "letter": "A"}
{"path": "speaker/Ross_Antonakos", "name": "Antonakos, Ross", "letter": "A"}
{"path": "speaker/Chris_Antone", "name": "Antone, Chris", "letter": "A"}
{"path": "speaker/Kristie_Anyabwile", "name": "Anyabwile, Kristie", "letter": "A"}
{"path": "speaker/Thabiti_Anyabwile", "name": "Anyabwile, Thabiti", "letter": "A"}
{"path": "speaker/Raphael_Anzenberger", "name": "Anzenberger, Raphael", "letter": "A"}
{"path": "speaker/Roy_Aparicio", "name": "Aparicio, Roy", "letter": "A"}
{"path": "speaker/Frank_Apisa", "name": "Apisa, Frank", "letter": "A"}
{"path": "speaker/Jimmy_Apodaca", "name": "Apodaca, Jimmy", "letter": "A"}
{"path": "speaker/Edgar_Aponte", "name": "Aponte, Edgar", "letter": "A"}
{"path": "speaker/Jed_Appell", "name": "Appell, Jed", "letter": "A"}
{"path": "speaker/Paul_Appere", "name": "Appere, Paul", "letter": "A"}
{"path": "speaker/Dr._David_Apple", "name": "Apple, David", "letter": "A"}
{"path": "speaker/Marvin_Apple", "name": "Apple, Marvin", "letter": "A"}
{"path": "speaker/Paul_Apple", "name": "Apple, Paul", "letter": "A"}
{"path": "speaker/John_Appleby", "name": "Appleby, John", "letter": "A"}
{"path": "speaker/Rick_Appleton", "name": "Appleton, Rick", "letter": "A"}
{"path": "speaker/Dominic_Aquila", "name": "Aquila, Dominic", "letter": "A"}
{"path": "speaker/H\u00e9ctor_Arag\u00f3n", "name": "Arag\u00f3n, H\u00e9ctor", "letter": "A"}
{"path": "speaker/Richard_Aragon", "name": "Aragon, Richard", "letter": "A"}
{"path": "speaker/Oliver_Araiza", "name": "Araiza, Oliver", "letter": "A"}
{"path": "speaker/Rev._Chris_Arcadi", "name": "Arcadi, Chris", "letter": "A"}
{"path": "speaker/Calixto_Arce", "name": "Arce, Calixto", "letter": "A"}
{"path": "speaker/Carlos_Arce", "name": "Arce, Carlos", "letter": "A"}
{"path": "speaker/Gregory_Arce", "name": "Arce, Gregory", "letter": "A"}
{"path": "speaker/David_Archambault", "name": "Archambault, David", "letter": "A"}
{"path": "speaker/Rev._Paul_Archbald", "name": "Archbald, Paul", "letter": "A"}
{"path": "speaker/Wes_Archer", "name": "Archer, Wes", "letter": "A"}
{"path": "speaker/Scott_Ardavanis", "name": "Ardavanis, Scott", "letter": "A"}
{"path": "speaker/Douglas_R._Ardis_Sr.", "name": "Ardis Sr, Douglas R", "letter": "A"}
{"path": "speaker/Randy_Ardis", "name": "Ardis, Randy", "letter": "A"}
{"path": "speaker/Adam_Ardizzoni", "name": "Ardizzoni, Adam", "letter": "A"}
{"path": "speaker/Charlie_Arehart", "name": "Arehart, Charlie", "letter": "A"}
{"path": "speaker/Kurt_Arehart", "name": "Arehart, Kurt", "letter": "A"}
{"path": "speaker/Pastor_Freddie_Arellano", "name": "Arellano, Freddie", "letter": "A"}
{"path": "speaker/Curt_Arend", "name": "Arend, Curt", "letter": "A"}
{"path": "speaker/Greg_Arend", "name": "Arend, Greg", "letter": "A"}
{"path": "speaker/Robert_Arendale", "name": "Arendale, Robert", "letter": "A"}
{"path": "speaker/Jason_Arens", "name": "Arens, Jason", "letter": "A"}
{"path": "speaker/Caesar_Arevalo", "name": "Arevalo, Caesar", "letter": "A"}
{"path": "speaker/Jonathan_Argo", "name": "Argo, Jonathan", "letter": "A"}
{"path": "speaker/V\u00edctor_Argudo", "name": "Argudo, V\u00edctor", "letter": "A"}
{"path": "speaker/Jos\u00e9_Antonio_Arias", "name": "Arias, Jos\u00e9 Antonio", "letter": "A"}
{"path": "speaker/Davis,_Arlan", "name": "Arlan, Davis,", "letter": "A"}
{"path": "speaker/Dan_Armacost", "name": "Armacost, Dan", "letter": "A"}
{"path": "speaker/Adrian_Armel", "name": "Armel, Adrian", "letter": "A"}
{"path": "speaker/Calvin_Armerding", "name": "Armerding, Calvin", "letter": "A"}
{"path": "speaker/Stan_Armes", "name": "Armes, Stan", "letter": "A"}
{"path": "speaker/Nathanael_Armisen", "name": "Armisen, Nathanael", "letter": "A"}
{"path": "speaker/Jim_Armour", "name": "Armour, Jim", "letter": "A"}
{"path": "speaker/Donn_Arms", "name": "Arms, Donn", "letter": "A"}
{"path": "speaker/Jimmy_Arms", "name": "Arms, Jimmy", "letter": "A"}
{"path": "speaker/Aaron_Armstrong", "name": "Armstrong, Aaron", "letter": "A"}
{"path": "speaker/Ben_Armstrong", "name": "Armstrong, Ben", "letter": "A"}
{"path": "speaker/Benjamin_Armstrong", "name": "Armstrong, Benjamin", "letter": "A"}
{"path": "speaker/Brent_Armstrong", "name": "Armstrong, Brent", "letter": "A"}
{"path": "speaker/C._J._Armstrong", "name": "Armstrong, C. J.", "letter": "A"}
{"path": "speaker/Rev._Charles_Armstrong", "name": "Armstrong, Charles", "letter": "A"}
{"path": "speaker/Don_Armstrong", "name": "Armstrong, Don", "letter": "A"}
{"path": "speaker/Gary_Armstrong", "name": "Armstrong, Gary", "letter": "A"}
{"path": "speaker/Jason_Armstrong", "name": "Armstrong, Jason", "letter": "A"}
{"path": "speaker/Rev._John_Armstrong", "name": "Armstrong, John", "letter": "A"}
{"path": "speaker/John_H._Armstrong", "name": "Armstrong, John H.", "letter": "A"}
{"path": "speaker/Jonh_Armstrong", "name": "Armstrong, Jonh", "letter": "A"}
{"path": "speaker/Mark_Armstrong", "name": "Armstrong, Mark", "letter": "A"}
{"path": "speaker/Matt_Armstrong", "name": "Armstrong, Matt", "letter": "A"}
{"path": "speaker/Nathan_Armstrong", "name": "Armstrong, Nathan", "letter": "A"}
{"path": "speaker/Peter_Armstrong", "name": "Armstrong, Peter", "letter": "A"}
{"path": "speaker/Rick_Armstrong", "name": "Armstrong, Rick", "letter": "A"}
{"path": "speaker/Seth_Armstrong", "name": "Armstrong, Seth", "letter": "A"}
{"path": "speaker/Stephen_Armstrong", "name": "Armstrong, Stephen", "letter": "A"}
{"path": "speaker/Tad_Armstrong", "name": "Armstrong, Tad", "letter": "A"}
{"path": "speaker/Zach_Armstrong", "name": "Armstrong, Zach", "letter": "A"}
{"path": "speaker/Jess_Arnds", "name": "Arnds, Jess", "letter": "A"}
{"path": "speaker/Dewain_Arndt", "name": "Arndt, Dewain", "letter": "A"}
{"path": "speaker/Johann_Arndt", "name": "Arndt, Johann", "letter": "A"}
{"path": "speaker/Will_Arndt", "name": "Arndt, Will", "letter": "A"}
{"path": "speaker/Elder_Lee_Arneson", "name": "Arneson, Lee", "letter": "A"}
{"path": "speaker/Benjamin_Arnold", "name": "Arnold, Benjamin", "letter": "A"}
{"path": "speaker/Brad_Arnold", "name": "Arnold, Brad", "letter": "A"}
{"path": "speaker/Daniel_Arnold", "name": "Arnold, Daniel", "letter": "A"}
{"path": "speaker/Dennis_Arnold", "name": "Arnold, Dennis", "letter": "A"}
{"path": "speaker/Dr._Harry_Arnold", "name": "Arnold, Harry", "letter": "A"}
{"path": "speaker/Hartford_Arnold", "name": "Arnold, Hartford", "letter": "A"}
{"path": "speaker/Mr._Hertford_Arnold", "name": "Arnold, Hertford", "letter": "A"}
{"path": "speaker/James_Arnold", "name": "Arnold, James", "letter": "A"}
{"path": "speaker/Jerrod_Arnold", "name": "Arnold, Jerrod", "letter": "A"}
{"path": "speaker/Jim_Arnold", "name": "Arnold, Jim", "letter": "A"}
{"path": "speaker/Joel_D._Arnold", "name": "Arnold, Joel D.", "letter": "A"}
{"path": "speaker/Jonathan_Arnold", "name": "Arnold, Jonathan", "letter": "A"}
{"path": "speaker/Phyllis_Arnold", "name": "Arnold, Phyllis", "letter": "A"}
{"path": "speaker/Steve_Arnold", "name": "Arnold, Steve", "letter": "A"}
{"path": "speaker/Rev_Terry_Arnold", "name": "Arnold, Terry", "letter": "A"}
{"path": "speaker/Vester_Arnold", "name": "Arnold, Vester", "letter": "A"}
{"path": "speaker/Blake_Arnoult", "name": "Arnoult, Blake", "letter": "A"}
{"path": "speaker/Oscar_Arocha", "name": "Arocha, Oscar", "letter": "A"}
{"path": "speaker/Missionary_Eddie_Arold", "name": "Arold, Eddie", "letter": "A"}
{"path": "speaker/Skip_Arp", "name": "Arp, Skip", "letter": "A"}
{"path": "speaker/William_Arp", "name": "Arp, William", "letter": "A"}
{"path": "speaker/Leo_Arriaga", "name": "Arriaga, Leo", "letter": "A"}
{"path": "speaker/Steve_Arrick", "name": "Arrick, Steve", "letter": "A"}
{"path": "speaker/Eddie_Arrindell", "name": "Arrindell, Eddie", "letter": "A"}
{"path": "speaker/Bert_Arrowood", "name": "Arrowood, Bert", "letter": "A"}
{"path": "speaker/Charles_Arrowood", "name": "Arrowood, Charles", "letter": "A"}
{"path": "speaker/Daniel_Bert_Arrowood", "name": "Arrowood, Daniel Bert", "letter": "A"}
{"path": "speaker/Jason_Arrowood", "name": "Arrowood, Jason", "letter": "A"}
{"path": "speaker/Rick_Arrowood", "name": "Arrowood, Rick", "letter": "A"}
{"path": "speaker/John_Arrowsmith", "name": "Arrowsmith, John", "letter": "A"}
{"path": "speaker/Simon_Arscott", "name": "Arscott, Simon", "letter": "A"}
{"path": "speaker/Gail_Arterburn", "name": "Arterburn, Gail", "letter": "A"}
{"path": "speaker/Jason_Arterburn", "name": "Arterburn, Jason", "letter": "A"}
{"path": "speaker/Vincent_A._Artese", "name": "Artese, Vincent A.", "letter": "A"}
{"path": "speaker/Vincent_G._Artese", "name": "Artese, Vincent G.", "letter": "A"}
{"path": "speaker/Jeff_Arthur_Jr.", "name": "Arthur Jr, Jeff", "letter": "A"}
{"path": "speaker/Brian_Arthur", "name": "Arthur, Brian", "letter": "A"}
{"path": "speaker/Darren_Arthur", "name": "Arthur, Darren", "letter": "A"}
{"path": "speaker/James_Arthur", "name": "Arthur, James", "letter": "A"}
{"path": "speaker/Jeff_Arthur", "name": "Arthur, Jeff", "letter": "A"}
{"path": "speaker/Joe_Arthur", "name": "Arthur, Joe", "letter": "A"}
{"path": "speaker/Phil_Arthur", "name": "Arthur, Phil", "letter": "A"}
{"path": "speaker/Timothy_Shay_Arthur", "name": "Arthur, Timothy Shay", "letter": "A"}
{"path": "speaker/Andrea_Artioli", "name": "Artioli, Andrea", "letter": "A"}
{"path": "speaker/David_Asaf", "name": "Asaf, David", "letter": "A"}
{"path": "speaker/Joe_Asbell", "name": "Asbell, Joe", "letter": "A"}
{"path": "speaker/Elder_Jerry_Asberry", "name": "Asberry, Jerry", "letter": "A"}
{"path": "speaker/David_Aschenmeier", "name": "Aschenmeier, David", "letter": "A"}
{"path": "speaker/Jerry_Ascher", "name": "Ascher, Jerry", "letter": "A"}
{"path": "speaker/Pastor_Mike_Ascher", "name": "Ascher, Mike", "letter": "A"}
{"path": "speaker/Pastor_Bill_Ascol", "name": "Ascol, Bill", "letter": "A"}
{"path": "speaker/Joshua_Ascol", "name": "Ascol, Joshua", "letter": "A"}
{"path": "speaker/Rev._Tom_Ascol", "name": "Ascol, Tom", "letter": "A"}
{"path": "speaker/David_Ash", "name": "Ash, David", "letter": "A"}
{"path": "speaker/Mark_Ashbaugh", "name": "Ashbaugh, Mark", "letter": "A"}
{"path": "speaker/John_Ashbrook", "name": "Ashbrook, John", "letter": "A"}
{"path": "speaker/Rev_John_E._Ashbrook", "name": "Ashbrook, John E.", "letter": "A"}
{"path": "speaker/Scott_Ashby", "name": "Ashby, Scott", "letter": "A"}
{"path": "speaker/Lanny_Ashcraft", "name": "Ashcraft, Lanny", "letter": "A"}
{"path": "speaker/Michael_Ashcraft", "name": "Ashcraft, Michael", "letter": "A"}
{"path": "speaker/Missionary_Ryan_Ashcraft", "name": "Ashcraft, Ryan", "letter": "A"}
{"path": "speaker/Tommy_Ashcraft", "name": "Ashcraft, Tommy", "letter": "A"}
{"path": "speaker/Ken_Ashcroft", "name": "Ashcroft, Ken", "letter": "A"}
{"path": "speaker/Robert_Ashe", "name": "Ashe, Robert", "letter": "A"}
{"path": "speaker/Tom_Ashe", "name": "Ashe, Tom", "letter": "A"}
{"path": "speaker/Casey_Asher", "name": "Asher, Casey", "letter": "A"}
{"path": "speaker/Dr._Bruce_Ashford", "name": "Ashford, Bruce", "letter": "A"}
{"path": "speaker/Dennis_Ashley", "name": "Ashley, Dennis", "letter": "A"}
{"path": "speaker/Dr._Ken_Ashlock", "name": "Ashlock, Ken", "letter": "A"}
{"path": "speaker/Scott_Ashmore", "name": "Ashmore, Scott", "letter": "A"}
{"path": "speaker/Steve_Ashmore", "name": "Ashmore, Steve", "letter": "A"}
{"path": "speaker/Thomas_Ashton", "name": "Ashton, Thomas", "letter": "A"}
{"path": "speaker/Pastor_John_Ashwood", "name": "Ashwood, John", "letter": "A"}
{"path": "speaker/Joshua_Ashwood", "name": "Ashwood, Joshua", "letter": "A"}
{"path": "speaker/Elder_Samuel_Ashwood", "name": "Ashwood, Samuel", "letter": "A"}
{"path": "speaker/Dale_Ashworth", "name": "Ashworth, Dale", "letter": "A"}
{"path": "speaker/Monte_Ashworth", "name": "Ashworth, Monte", "letter": "A"}
{"path": "speaker/William_Ashworth", "name": "Ashworth, William", "letter": "A"}
{"path": "speaker/Mario_Asis", "name": "Asis, Mario", "letter": "A"}
{"path": "speaker/Chuck_Askew", "name": "Askew, Chuck", "letter": "A"}
{"path": "speaker/Mark_Askew", "name": "Askew, Mark", "letter": "A"}
{"path": "speaker/Pius_Asoegwu", "name": "Asoegwu, Pius", "letter": "A"}
{"path": "speaker/Assoc_Session_Xenia,_Ohio", "name": "Assoc Session Xenia, Ohio", "letter": "A"}
{"path": "speaker/Agustin_Astacio", "name": "Astacio, Agustin", "letter": "A"}
{"path": "speaker/Missionary_Elmer_Astillero", "name": "Astillero, Elmer", "letter": "A"}
{"path": "speaker/Samuel_Asuma", "name": "Asuma, Samuel", "letter": "A"}
{"path": "speaker/David_Aszbach", "name": "Aszbach, David", "letter": "A"}
{"path": "speaker/Matthew_Atack", "name": "Atack, Matthew", "letter": "A"}
{"path": "speaker/Tom_Atack", "name": "Atack, Tom", "letter": "A"}
{"path": "speaker/Victor_Atallah", "name": "Atallah, Victor", "letter": "A"}
{"path": "speaker/Jude_Atas", "name": "Atas, Jude", "letter": "A"}
{"path": "speaker/Paul_Atcheson", "name": "Atcheson, Paul", "letter": "A"}
{"path": "speaker/Claude_Atcho", "name": "Atcho, Claude", "letter": "A"}
{"path": "speaker/Sherif_Atef", "name": "Atef, Sherif", "letter": "A"}
{"path": "speaker/Art_Athens", "name": "Athens, Art", "letter": "A"}
{"path": "speaker/Steve_Atkerson", "name": "Atkerson, Steve", "letter": "A"}
{"path": "speaker/Pastor_Alpheus_Atkins", "name": "Atkins, Alpheus", "letter": "A"}
{"path": "speaker/Jim_Atkins", "name": "Atkins, Jim", "letter": "A"}
{"path": "speaker/Roger_Atkins", "name": "Atkins, Roger", "letter": "A"}
{"path": "speaker/Tim_Atkins", "name": "Atkins, Tim", "letter": "A"}
{"path": "speaker/Brent_Atkinson", "name": "Atkinson, Brent", "letter": "A"}
{"path": "speaker/Clay_Atkinson", "name": "Atkinson, Clay", "letter": "A"}
{"path": "speaker/David_Atkinson", "name": "Atkinson, David", "letter": "A"}
{"path": "speaker/Dr._David_M._Atkinson", "name": "Atkinson, David M.", "letter": "A"}
{"path": "speaker/Jarrett_Atkinson", "name": "Atkinson, Jarrett", "letter": "A"}
{"path": "speaker/Lee_Atkinson", "name": "Atkinson, Lee", "letter": "A"}
{"path": "speaker/Lynn_Atkinson", "name": "Atkinson, Lynn", "letter": "A"}
{"path": "speaker/Stephen_Atkinson", "name": "Atkinson, Stephen", "letter": "A"}
{"path": "speaker/Rev._Terence_Atkinson", "name": "Atkinson, Terence", "letter": "A"}
{"path": "speaker/Bruce_Atkisson", "name": "Atkisson, Bruce", "letter": "A"}
{"path": "speaker/Matthew_Atteberry", "name": "Atteberry, Matthew", "letter": "A"}
{"path": "speaker/Philip_Attebery", "name": "Attebery, Philip", "letter": "A"}
{"path": "speaker/Scott_Attebery", "name": "Attebery, Scott", "letter": "A"}
{"path": "speaker/Mr._Wally_Atten", "name": "Atten, Wally", "letter": "A"}
{"path": "speaker/Keith_Williams,_Attorney", "name": "Attorney, Keith Williams,", "letter": "A"}
{"path": "speaker/Mike_Attwood", "name": "Attwood, Mike", "letter": "A"}
{"path": "speaker/Nelson_Attwood", "name": "Attwood, Nelson", "letter": "A"}
{"path": "speaker/Brad_Atwell", "name": "Atwell, Brad", "letter": "A"}
{"path": "speaker/Joe_Atwell", "name": "Atwell, Joe", "letter": "A"}
{"path": "speaker/Jason_Atwood", "name": "Atwood, Jason", "letter": "A"}
{"path": "speaker/Rev._Nathan_Atwood", "name": "Atwood, Nathan", "letter": "A"}
{"path": "speaker/Elder_Alan_Aubel", "name": "Aubel, Alan", "letter": "A"}
{"path": "speaker/Imad_Aubrey", "name": "Aubrey, Imad", "letter": "A"}
{"path": "speaker/Joel_Aubrey", "name": "Aubrey, Joel", "letter": "A"}
{"path": "speaker/Hein_Aucamp", "name": "Aucamp, Hein", "letter": "A"}
{"path": "speaker/Johannes_Aucamp", "name": "Aucamp, Johannes", "letter": "A"}
{"path": "speaker/Elder_Bob_Auckland", "name": "Auckland, Bob", "letter": "A"}
{"path": "speaker/Paul_Auckland", "name": "Auckland, Paul", "letter": "A"}
{"path": "speaker/Brent_Aucoin", "name": "Aucoin, Brent", "letter": "A"}
{"path": "speaker/Brent_J_Aucoin", "name": "Aucoin, Brent J", "letter": "A"}
{"path": "speaker/Aaron_Auer", "name": "Auer, Aaron", "letter": "A"}
{"path": "speaker/Mike_Auger", "name": "Auger, Mike", "letter": "A"}
{"path": "speaker/Lance_Augsburger", "name": "Augsburger, Lance", "letter": "A"}
{"path": "speaker/Aurelius_Augustine", "name": "Augustine, Aurelius", "letter": "A"}
{"path": "speaker/Stephen_Aulino", "name": "Aulino, Stephen", "letter": "A"}
{"path": "speaker/Nathan_Ault", "name": "Ault, Nathan", "letter": "A"}
{"path": "speaker/Joshua_Aumaea", "name": "Aumaea, Joshua", "letter": "A"}
{"path": "speaker/Paul_Austen", "name": "Austen, Paul", "letter": "A"}
{"path": "speaker/Bryan_Austin", "name": "Austin, Bryan", "letter": "A"}
{"path": "speaker/Dann_Austin", "name": "Austin, Dann", "letter": "A"}
{"path": "speaker/Dr._Jim_Austin", "name": "Austin, Jim", "letter": "A"}
{"path": "speaker/Matthew_Austin", "name": "Austin, Matthew", "letter": "A"}
{"path": "speaker/Mickey_Austin", "name": "Austin, Mickey", "letter": "A"}
{"path": "speaker/Mike_Austin", "name": "Austin, Mike", "letter": "A"}
{"path": "speaker/Paul_Austin", "name": "Austin, Paul", "letter": "A"}
{"path": "speaker/Ryan_Austin", "name": "Austin, Ryan", "letter": "A"}
{"path": "speaker/Seth_Austin", "name": "Austin, Seth", "letter": "A"}
{"path": "speaker/Dr._Steven_Austin", "name": "Austin, Steven", "letter": "A"}
{"path": "speaker/Dr._Tom_Austin", "name": "Austin, Tom", "letter": "A"}
{"path": "speaker/Frank_Auterson", "name": "Auterson, Frank", "letter": "A"}
{"path": "speaker/Chris_Autry", "name": "Autry, Chris", "letter": "A"}
{"path": "speaker/Lanny_Autry", "name": "Autry, Lanny", "letter": "A"}
{"path": "speaker/Scott_Autry", "name": "Autry, Scott", "letter": "A"}
{"path": "speaker/Dave_Auxier", "name": "Auxier, Dave", "letter": "A"}
{"path": "speaker/HauTzeng_AuYeong", "name": "AuYeong, HauTzeng", "letter": "A"}
{"path": "speaker/Emmanuel_Avalos", "name": "Avalos, Emmanuel", "letter": "A"}
{"path": "speaker/Jossue_Avalos", "name": "Avalos, Jossue", "letter": "A"}
{"path": "speaker/William_Avants", "name": "Avants, William", "letter": "A"}
{"path": "speaker/Manny_Avena", "name": "Avena, Manny", "letter": "A"}
{"path": "speaker/Giovanni_Avendano", "name": "Avendano, Giovanni", "letter": "A"}
{"path": "speaker/L'Avenir", "name": "Avenir, L", "letter": "A"}
{"path": "speaker/Alan_Avera", "name": "Avera, Alan", "letter": "A"}
{"path": "speaker/Harlan_Avera", "name": "Avera, Harlan", "letter": "A"}
{"path": "speaker/Jeff_Avery", "name": "Avery, Jeff", "letter": "A"}
{"path": "speaker/Bro._Ken_Avery", "name": "Avery, Ken", "letter": "A"}
{"path": "speaker/Fabian_Avila", "name": "Avila, Fabian", "letter": "A"}
{"path": "speaker/Joel_Madlang_Awa", "name": "Awa, Joel Madlang", "letter": "A"}
{"path": "speaker/Danny_Awad", "name": "Awad, Danny", "letter": "A"}
{"path": "speaker/Karam_Awad", "name": "Awad, Karam", "letter": "A"}
{"path": "speaker/Ben_Awbrey", "name": "Awbrey, Ben", "letter": "A"}
{"path": "speaker/Chulho_Awe", "name": "Awe, Chulho", "letter": "A"}
{"path": "speaker/Pastor_Matthew_D._Awtrey", "name": "Awtrey, Matthew D.", "letter": "A"}
{"path": "speaker/Mike_Awtry", "name": "Awtry, Mike", "letter": "A"}
{"path": "speaker/Tim_Axell", "name": "Axell, Tim", "letter": "A"}
{"path": "speaker/Mitch_Axsom", "name": "Axsom, Mitch", "letter": "A"}
{"path": "speaker/Nathan_Axtell", "name": "Axtell, Nathan", "letter": "A"}
{"path": "speaker/Jim_Aydelotte", "name": "Aydelotte, Jim", "letter": "A"}
{"path": "speaker/Flynn_Ayers", "name": "Ayers, Flynn", "letter": "A"}
{"path": "speaker/Fred_Ayers", "name": "Ayers, Fred", "letter": "A"}
{"path": "speaker/Josh_Ayers", "name": "Ayers, Josh", "letter": "A"}
{"path": "speaker/Dr._Mike_Ayers", "name": "Ayers, Mike", "letter": "A"}
{"path": "speaker/Mike_Aylestock", "name": "Aylestock, Mike", "letter": "A"}
{"path": "speaker/Samuel_Aylestock", "name": "Aylestock, Samuel", "letter": "A"}
{"path": "speaker/Tim_Aynes", "name": "Aynes, Tim", "letter": "A"}
{"path": "speaker/Robert_Ayoub", "name": "Ayoub, Robert", "letter": "A"}
{"path": "speaker/Missionary_Billy_Ayre", "name": "Ayre, Billy", "letter": "A"}
{"path": "speaker/Chelsea_Ayres", "name": "Ayres, Chelsea", "letter": "A"}
{"path": "speaker/David_Ayres", "name": "Ayres, David", "letter": "A"}
{"path": "speaker/Jacob_Ayres", "name": "Ayres, Jacob", "letter": "A"}
{"path": "speaker/Kyle_Ayres", "name": "Ayres, Kyle", "letter": "A"}
{"path": "speaker/Michael_Ayres", "name": "Ayres, Michael", "letter": "A"}
{"path": "speaker/Nathan_Ayres", "name": "Ayres, Nathan", "letter": "A"}
{"path": "speaker/David_Azarello", "name": "Azarello, David", "letter": "A"}
{"path": "speaker/YesuDas_Azariah", "name": "Azariah, YesuDas", "letter": "A"}
{"path": "speaker/Arturo_G._Azurdia_III", "name": "Azurdia III, Arturo G.", "letter": "A"}
{"path": "speaker/Art_Azurdia", "name": "Azurdia, Art", "letter": "A"}
{"path": "speaker/David_Azzarello", "name": "Azzarello, David", "letter": "A"}
{"path": "speaker/David_Azzarelo", "name": "Azzarelo, David", "letter": "A"}
